autodcf/__init__.py
autodcf/company/__init__.py
autodcf/company/balance_sheet.py
autodcf/company/cash_flows.py
autodcf/company/company.py
autodcf/company/income_statement.py
autodcf/models/__init__.py
autodcf/models/_base.py
autodcf/models/dcf.py
autodcf/models/simple_dcf.py
autodcf/tests/__init__.py
autodcf/tests/conftest.py
autodcf/tests/utils.py
autodcf/tests/company/__init__.py
autodcf/tests/company/test_balance_sheet.py
autodcf/tests/company/test_cash_flows.py
autodcf/tests/company/test_company.py
autodcf/tests/company/test_income_statement.py
autodcf/tests/models/__init__.py
autodcf/tests/models/test_dcf.py
autodcf/tests/models/test_simple_dcf.py
autodcf-0.1.0.dist-info/LICENSE
autodcf-0.1.0.dist-info/METADATA
autodcf-0.1.0.dist-info/WHEEL
autodcf-0.1.0.dist-info/entry_points.txt
autodcf-0.1.0.dist-info/top_level.txt
autodcf-0.1.0.dist-info/RECORD
