Metadata-Version: 2.1
Name: autodcf
Version: 0.1.0
Summary: Build discounted cash flow (DCF) models with ease. Allows for advanced manipulation
Home-page: https://github.com/jackmoody11/autodcf
Author: Jack Moody
Author-email: moodyjack11@gmail.com
License: MIT License
Download-URL: https://github.com/jackmoody11/autodcf/releases
Keywords: DCF,Discounted Cash Flow,finance
Platform: UNKNOWN
Classifier: Environment :: Console
Classifier: License :: OSI Approved :: Apache Software License
Classifier: Operating System :: OS Independent
Classifier: Programming Language :: Python
Classifier: Topic :: Software Development :: Libraries :: Python Modules
Classifier: Programming Language :: Python :: 3.5
Classifier: Programming Language :: Python :: 3.6
Classifier: Programming Language :: Python :: 3.7
Classifier: Programming Language :: Python :: 3.8
Requires-Dist: pandas
Requires-Dist: numpy
